awsmanifest/__init__.py
awsmanifest/policies.js
aws_manifest-0.1.0.dist-info/METADATA
aws_manifest-0.1.0.dist-info/WHEEL
aws_manifest-0.1.0.dist-info/top_level.txt
aws_manifest-0.1.0.dist-info/RECORD
