Metadata-Version: 2.1
Name: aws-manifest
Version: 0.1.0
Summary: Package for retrieving aws resource names and their actions
Home-page: https://github.com/dang3r/aws-actions
Author: Daniel Cardoza
Author-email: dan@danielcardoza.com
License: MIT
Platform: UNKNOWN
Requires-Python: >=3.4.0
Requires-Dist: requests
Requires-Dist: pytest
